{"form": [{"box": [200, 238, 284, 266], "text": "Name:", "label": "other", "id": 0, "words": [{"box": [200, 238, 284, 266], "text": "Name:"}]}, {"box": [289, 238, 339, 266], "text": "Tan", "label": "name", "id": 1, "words": [{"box": [289, 238, 339, 266], "text": "Tan"}]}, {"box": [344, 238, 443, 266], "text": "Quanlin", "label": "name", "id": 2, "words": [{"box": [344, 238, 443, 266], "text": "Quanlin"}]}, {"box": [200, 298, 284, 326], "text": "Mobile", "label": "other", "id": 3, "words": [{"box": [200, 298, 284, 326], "text": "Mobile"}]}, {"box": [289, 298, 398, 326], "text": "Number:", "label": "other", "id": 4, "words": [{"box": [289, 298, 398, 326], "text": "Number:"}]}, {"box": [403, 298, 455, 326], "text": "(65)", "label": "phone", "id": 5, "words": [{"box": [403, 298, 455, 326], "text": "(65)"}]}, {"box": [460, 298, 524, 326], "text": "9114", "label": "phone", "id": 6, "words": [{"box": [460, 298, 524, 326], "text": "9114"}]}, {"box": [530, 298, 594, 326], "text": "5574", "label": "phone", "id": 7, "words": [{"box": [530, 298, 594, 326], "text": "5574"}]}, {"box": [200, 358, 288, 385], "text": "E-Mail:", "label": "other", "id": 8, "words": [{"box": [200, 358, 288, 385], "text": "E-Mail:"}]}, {"box": [293, 358, 579, 385], "text": "tanquanlin@gmail.com", "label": "email", "id": 9, "words": [{"box": [293, 358, 579, 385], "text": "tanquanlin@gmail.com"}]}, {"box": [200, 418, 255, 445], "text": "Last", "label": "other", "id": 10, "words": [{"box": [200, 418, 255, 445], "text": "Last"}]}, {"box": [260, 418, 350, 445], "text": "Drawn:", "label": "other", "id": 11, "words": [{"box": [260, 418, 350, 445], "text": "Drawn:"}]}, {"box": [355, 418, 419, 445], "text": "4000", "label": "other", "id": 12, "words": [{"box": [355, 418, 419, 445], "text": "4000"}]}, {"box": [425, 418, 572, 445], "text": "SGD/Month", "label": "other", "id": 13, "words": [{"box": [425, 418, 572, 445], "text": "SGD/Month"}]}, {"box": [200, 477, 295, 505], "text": "Earliest", "label": "other", "id": 14, "words": [{"box": [200, 477, 295, 505], "text": "Earliest"}]}, {"box": [300, 477, 441, 505], "text": "Availability:", "label": "other", "id": 15, "words": [{"box": [300, 477, 441, 505], "text": "Availability:"}]}, {"box": [446, 477, 464, 505], "text": "1", "label": "other", "id": 16, "words": [{"box": [446, 477, 464, 505], "text": "1"}]}, {"box": [469, 477, 549, 505], "text": "Month", "label": "other", "id": 17, "words": [{"box": [469, 477, 549, 505], "text": "Month"}]}, {"box": [554, 477, 635, 505], "text": "Notice", "label": "other", "id": 18, "words": [{"box": [554, 477, 635, 505], "text": "Notice"}]}, {"box": [200, 537, 353, 565], "text": "PERSONAL", "label": "other", "id": 19, "words": [{"box": [200, 537, 353, 565], "text": "PERSONAL"}]}, {"box": [358, 537, 529, 565], "text": "STATEMENT", "label": "other", "id": 20, "words": [{"box": [358, 537, 529, 565], "text": "STATEMENT"}]}, {"box": [200, 597, 236, 624], "text": "An", "label": "other", "id": 21, "words": [{"box": [200, 597, 236, 624], "text": "An"}]}, {"box": [241, 597, 339, 624], "text": "efficient", "label": "other", "id": 22, "words": [{"box": [241, 597, 339, 624], "text": "efficient"}]}, {"box": [344, 597, 430, 624], "text": "worker", "label": "other", "id": 23, "words": [{"box": [344, 597, 430, 624], "text": "worker"}]}, {"box": [435, 597, 487, 624], "text": "with", "label": "other", "id": 24, "words": [{"box": [435, 597, 487, 624], "text": "with"}]}, {"box": [492, 597, 566, 624], "text": "ability", "label": "other", "id": 25, "words": [{"box": [492, 597, 566, 624], "text": "ability"}]}, {"box": [571, 597, 597, 624], "text": "to", "label": "other", "id": 26, "words": [{"box": [571, 597, 597, 624], "text": "to"}]}, {"box": [602, 597, 674, 624], "text": "adapt", "label": "other", "id": 27, "words": [{"box": [602, 597, 674, 624], "text": "adapt"}]}, {"box": [679, 597, 728, 624], "text": "and", "label": "other", "id": 28, "words": [{"box": [679, 597, 728, 624], "text": "and"}]}, {"box": [733, 597, 798, 624], "text": "learn", "label": "other", "id": 29, "words": [{"box": [733, 597, 798, 624], "text": "learn"}]}, {"box": [803, 597, 858, 624], "text": "fast,", "label": "other", "id": 30, "words": [{"box": [803, 597, 858, 624], "text": "fast,"}]}, {"box": [863, 597, 917, 624], "text": "who", "label": "other", "id": 31, "words": [{"box": [863, 597, 917, 624], "text": "who"}]}, {"box": [922, 597, 944, 624], "text": "is", "label": "other", "id": 32, "words": [{"box": [922, 597, 944, 624], "text": "is"}]}, {"box": [950, 597, 1105, 624], "text": "independant", "label": "other", "id": 33, "words": [{"box": [950, 597, 1105, 624], "text": "independant"}]}, {"box": [1110, 597, 1159, 624], "text": "and", "label": "other", "id": 34, "words": [{"box": [1110, 597, 1159, 624], "text": "and"}]}, {"box": [1164, 597, 1287, 624], "text": "confident,", "label": "other", "id": 35, "words": [{"box": [1164, 597, 1287, 624], "text": "confident,"}]}, {"box": [1292, 597, 1367, 624], "text": "seeks", "label": "other", "id": 36, "words": [{"box": [1292, 597, 1367, 624], "text": "seeks"}]}, {"box": [1372, 597, 1390, 624], "text": "a", "label": "other", "id": 37, "words": [{"box": [1372, 597, 1390, 624], "text": "a"}]}, {"box": [1395, 597, 1443, 624], "text": "fast", "label": "other", "id": 38, "words": [{"box": [1395, 597, 1443, 624], "text": "fast"}]}, {"box": [200, 629, 278, 656], "text": "paced", "label": "other", "id": 39, "words": [{"box": [200, 629, 278, 656], "text": "paced"}]}, {"box": [283, 629, 438, 656], "text": "environment", "label": "other", "id": 40, "words": [{"box": [283, 629, 438, 656], "text": "environment"}]}, {"box": [443, 629, 469, 656], "text": "to", "label": "other", "id": 41, "words": [{"box": [443, 629, 469, 656], "text": "to"}]}, {"box": [474, 629, 541, 656], "text": "excel", "label": "other", "id": 42, "words": [{"box": [474, 629, 541, 656], "text": "excel"}]}, {"box": [546, 629, 578, 656], "text": "in.", "label": "other", "id": 43, "words": [{"box": [546, 629, 578, 656], "text": "in."}]}, {"box": [200, 688, 318, 716], "text": "CAREER", "label": "other", "id": 44, "words": [{"box": [200, 688, 318, 716], "text": "CAREER"}]}, {"box": [322, 688, 480, 716], "text": "OBJECTIVE", "label": "other", "id": 45, "words": [{"box": [322, 688, 480, 716], "text": "OBJECTIVE"}]}, {"box": [200, 748, 301, 776], "text": "Building", "label": "other", "id": 46, "words": [{"box": [200, 748, 301, 776], "text": "Building"}]}, {"box": [306, 748, 339, 776], "text": "up", "label": "other", "id": 47, "words": [{"box": [306, 748, 339, 776], "text": "up"}]}, {"box": [344, 748, 384, 776], "text": "my", "label": "other", "id": 48, "words": [{"box": [344, 748, 384, 776], "text": "my"}]}, {"box": [389, 748, 490, 776], "text": "portfolio", "label": "other", "id": 49, "words": [{"box": [389, 748, 490, 776], "text": "portfolio"}]}, {"box": [495, 748, 545, 776], "text": "and", "label": "other", "id": 50, "words": [{"box": [495, 748, 545, 776], "text": "and"}]}, {"box": [550, 748, 694, 776], "text": "accumulate", "label": "other", "id": 51, "words": [{"box": [550, 748, 694, 776], "text": "accumulate"}]}, {"box": [699, 748, 838, 776], "text": "experience", "label": "other", "id": 52, "words": [{"box": [699, 748, 838, 776], "text": "experience"}]}, {"box": [843, 748, 867, 776], "text": "in", "label": "other", "id": 53, "words": [{"box": [843, 748, 867, 776], "text": "in"}]}, {"box": [872, 748, 913, 776], "text": "the", "label": "other", "id": 54, "words": [{"box": [872, 748, 913, 776], "text": "the"}]}, {"box": [918, 748, 1023, 776], "text": "financial", "label": "other", "id": 55, "words": [{"box": [918, 748, 1023, 776], "text": "financial"}]}, {"box": [1028, 748, 1106, 776], "text": "sector", "label": "other", "id": 56, "words": [{"box": [1028, 748, 1106, 776], "text": "sector"}]}, {"box": [1111, 748, 1160, 776], "text": "that", "label": "other", "id": 57, "words": [{"box": [1111, 748, 1160, 776], "text": "that"}]}, {"box": [1165, 748, 1234, 776], "text": "leads", "label": "other", "id": 58, "words": [{"box": [1165, 748, 1234, 776], "text": "leads"}]}, {"box": [1239, 748, 1265, 776], "text": "to", "label": "other", "id": 59, "words": [{"box": [1239, 748, 1265, 776], "text": "to"}]}, {"box": [1270, 748, 1356, 776], "text": "growth", "label": "other", "id": 60, "words": [{"box": [1270, 748, 1356, 776], "text": "growth"}]}, {"box": [1361, 748, 1385, 776], "text": "in", "label": "other", "id": 61, "words": [{"box": [1361, 748, 1385, 776], "text": "in"}]}, {"box": [1390, 748, 1430, 776], "text": "my", "label": "other", "id": 62, "words": [{"box": [1390, 748, 1430, 776], "text": "my"}]}, {"box": [200, 780, 352, 808], "text": "professional", "label": "other", "id": 63, "words": [{"box": [200, 780, 352, 808], "text": "professional"}]}, {"box": [357, 780, 419, 808], "text": "skills", "label": "other", "id": 64, "words": [{"box": [357, 780, 419, 808], "text": "skills"}]}, {"box": [425, 780, 473, 808], "text": "and", "label": "other", "id": 65, "words": [{"box": [425, 780, 473, 808], "text": "and"}]}, {"box": [478, 780, 614, 808], "text": "knowledge", "label": "other", "id": 66, "words": [{"box": [478, 780, 614, 808], "text": "knowledge"}]}, {"box": [619, 780, 692, 808], "text": "which", "label": "other", "id": 67, "words": [{"box": [619, 780, 692, 808], "text": "which"}]}, {"box": [697, 780, 745, 808], "text": "can", "label": "other", "id": 68, "words": [{"box": [697, 780, 745, 808], "text": "can"}]}, {"box": [750, 780, 878, 808], "text": "applicable", "label": "other", "id": 69, "words": [{"box": [750, 780, 878, 808], "text": "applicable"}]}, {"box": [883, 780, 952, 808], "text": "when", "label": "other", "id": 70, "words": [{"box": [883, 780, 952, 808], "text": "when"}]}, {"box": [957, 780, 1048, 808], "text": "striving", "label": "other", "id": 71, "words": [{"box": [957, 780, 1048, 808], "text": "striving"}]}, {"box": [1053, 780, 1088, 808], "text": "for", "label": "other", "id": 72, "words": [{"box": [1053, 780, 1088, 808], "text": "for"}]}, {"box": [1093, 780, 1134, 808], "text": "the", "label": "other", "id": 73, "words": [{"box": [1093, 780, 1134, 808], "text": "the"}]}, {"box": [1139, 780, 1225, 808], "text": "growth", "label": "other", "id": 74, "words": [{"box": [1139, 780, 1225, 808], "text": "growth"}]}, {"box": [1230, 780, 1256, 808], "text": "of", "label": "other", "id": 75, "words": [{"box": [1230, 780, 1256, 808], "text": "of"}]}, {"box": [1261, 780, 1301, 808], "text": "my", "label": "other", "id": 76, "words": [{"box": [1261, 780, 1301, 808], "text": "my"}]}, {"box": [1306, 780, 1387, 808], "text": "career", "label": "other", "id": 77, "words": [{"box": [1306, 780, 1387, 808], "text": "career"}]}, {"box": [1392, 780, 1424, 808], "text": "as", "label": "other", "id": 78, "words": [{"box": [1392, 780, 1424, 808], "text": "as"}]}, {"box": [1429, 780, 1480, 808], "text": "well", "label": "other", "id": 79, "words": [{"box": [1429, 780, 1480, 808], "text": "well"}]}, {"box": [1485, 780, 1517, 808], "text": "as", "label": "other", "id": 80, "words": [{"box": [1485, 780, 1517, 808], "text": "as"}]}, {"box": [200, 812, 241, 840], "text": "the", "label": "other", "id": 81, "words": [{"box": [200, 812, 241, 840], "text": "the"}]}, {"box": [246, 812, 407, 840], "text": "organisation.", "label": "other", "id": 82, "words": [{"box": [246, 812, 407, 840], "text": "organisation."}]}, {"box": [200, 872, 365, 899], "text": "EDUCATION", "label": "other", "id": 83, "words": [{"box": [200, 872, 365, 899], "text": "EDUCATION"}]}, {"box": [200, 937, 329, 965], "text": "Singapore", "label": "school_name", "id": 84, "words": [{"box": [200, 937, 329, 965], "text": "Singapore"}]}, {"box": [333, 937, 433, 965], "text": "Institute", "label": "school_name", "id": 85, "words": [{"box": [333, 937, 433, 965], "text": "Institute"}]}, {"box": [438, 937, 464, 965], "text": "of", "label": "school_name", "id": 86, "words": [{"box": [438, 937, 464, 965], "text": "of"}]}, {"box": [469, 937, 634, 965], "text": "Management", "label": "school_name", "id": 87, "words": [{"box": [469, 937, 634, 965], "text": "Management"}]}, {"box": [639, 937, 709, 965], "text": "(SIM)", "label": "school_name", "id": 88, "words": [{"box": [639, 937, 709, 965], "text": "(SIM)"}]}, {"box": [1199, 937, 1264, 965], "text": "2011", "label": "school_date", "id": 89, "words": [{"box": [1199, 937, 1264, 965], "text": "2011"}]}, {"box": [1269, 937, 1294, 965], "text": "to", "label": "school_date", "id": 90, "words": [{"box": [1269, 937, 1294, 965], "text": "to"}]}, {"box": [1300, 937, 1364, 965], "text": "2014", "label": "school_date", "id": 91, "words": [{"box": [1300, 937, 1364, 965], "text": "2014"}]}, {"box": [200, 997, 324, 1024], "text": "University", "label": "school_name", "id": 92, "words": [{"box": [200, 997, 324, 1024], "text": "University"}]}, {"box": [329, 997, 355, 1024], "text": "of", "label": "school_name", "id": 93, "words": [{"box": [329, 997, 355, 1024], "text": "of"}]}, {"box": [360, 997, 455, 1024], "text": "London", "label": "school_name", "id": 94, "words": [{"box": [360, 997, 455, 1024], "text": "London"}]}, {"box": [299, 1058, 411, 1086], "text": "Bachelor", "label": "major", "id": 95, "words": [{"box": [299, 1058, 411, 1086], "text": "Bachelor"}]}, {"box": [416, 1058, 442, 1086], "text": "of", "label": "major", "id": 96, "words": [{"box": [416, 1058, 442, 1086], "text": "of"}]}, {"box": [447, 1058, 549, 1086], "text": "Science", "label": "major", "id": 97, "words": [{"box": [447, 1058, 549, 1086], "text": "Science"}]}, {"box": [554, 1058, 578, 1086], "text": "in", "label": "major", "id": 98, "words": [{"box": [554, 1058, 578, 1086], "text": "in"}]}, {"box": [583, 1058, 686, 1086], "text": "Banking", "label": "major", "id": 99, "words": [{"box": [583, 1058, 686, 1086], "text": "Banking"}]}, {"box": [691, 1058, 713, 1086], "text": "&", "label": "major", "id": 100, "words": [{"box": [691, 1058, 713, 1086], "text": "&"}]}, {"box": [717, 1058, 819, 1086], "text": "Finance", "label": "major", "id": 101, "words": [{"box": [717, 1058, 819, 1086], "text": "Finance"}]}, {"box": [299, 1120, 433, 1147], "text": "Graduated", "label": "other", "id": 102, "words": [{"box": [299, 1120, 433, 1147], "text": "Graduated"}]}, {"box": [438, 1120, 490, 1147], "text": "with", "label": "other", "id": 103, "words": [{"box": [438, 1120, 490, 1147], "text": "with"}]}, {"box": [495, 1120, 513, 1147], "text": "2", "label": "other", "id": 104, "words": [{"box": [495, 1120, 513, 1147], "text": "2"}]}, {"box": [538, 1120, 617, 1147], "text": "Upper", "label": "other", "id": 105, "words": [{"box": [538, 1120, 617, 1147], "text": "Upper"}]}, {"box": [622, 1120, 694, 1147], "text": "Class", "label": "other", "id": 106, "words": [{"box": [622, 1120, 694, 1147], "text": "Class"}]}, {"box": [699, 1120, 806, 1147], "text": "Honours", "label": "other", "id": 107, "words": [{"box": [699, 1120, 806, 1147], "text": "Honours"}]}, {"box": [511, 1119, 534, 1137], "text": "nd", "label": "other", "id": 108, "words": [{"box": [511, 1119, 534, 1137], "text": "nd"}]}, {"box": [200, 1179, 316, 1207], "text": "Temasek", "label": "school_name", "id": 109, "words": [{"box": [200, 1179, 316, 1207], "text": "Temasek"}]}, {"box": [321, 1179, 466, 1207], "text": "Polytechnic", "label": "school_name", "id": 110, "words": [{"box": [321, 1179, 466, 1207], "text": "Polytechnic"}]}, {"box": [1199, 1179, 1264, 1207], "text": "2006", "label": "school_date", "id": 111, "words": [{"box": [1199, 1179, 1264, 1207], "text": "2006"}]}, {"box": [1269, 1179, 1294, 1207], "text": "to", "label": "school_date", "id": 112, "words": [{"box": [1269, 1179, 1294, 1207], "text": "to"}]}, {"box": [1300, 1179, 1364, 1207], "text": "2009", "label": "school_date", "id": 113, "words": [{"box": [1300, 1179, 1364, 1207], "text": "2009"}]}, {"box": [299, 1241, 404, 1269], "text": "Diploma", "label": "other", "id": 114, "words": [{"box": [299, 1241, 404, 1269], "text": "Diploma"}]}, {"box": [409, 1241, 433, 1269], "text": "in", "label": "other", "id": 115, "words": [{"box": [409, 1241, 433, 1269], "text": "in"}]}, {"box": [438, 1241, 566, 1269], "text": "Integrated", "label": "other", "id": 116, "words": [{"box": [438, 1241, 566, 1269], "text": "Integrated"}]}, {"box": [571, 1241, 681, 1269], "text": "Facilities", "label": "other", "id": 117, "words": [{"box": [571, 1241, 681, 1269], "text": "Facilities"}]}, {"box": [686, 1241, 776, 1269], "text": "Design", "label": "other", "id": 118, "words": [{"box": [686, 1241, 776, 1269], "text": "Design"}]}, {"box": [781, 1241, 829, 1269], "text": "and", "label": "other", "id": 119, "words": [{"box": [781, 1241, 829, 1269], "text": "and"}]}, {"box": [835, 1241, 1000, 1269], "text": "Management", "label": "other", "id": 120, "words": [{"box": [835, 1241, 1000, 1269], "text": "Management"}]}, {"box": [299, 1303, 361, 1330], "text": "GPA", "label": "grade", "id": 121, "words": [{"box": [299, 1303, 361, 1330], "text": "GPA"}]}, {"box": [366, 1303, 422, 1330], "text": "2.88", "label": "grade", "id": 122, "words": [{"box": [366, 1303, 422, 1330], "text": "2.88"}]}, {"box": [200, 1362, 338, 1390], "text": "Serangoon", "label": "school_name", "id": 123, "words": [{"box": [200, 1362, 338, 1390], "text": "Serangoon"}]}, {"box": [343, 1362, 478, 1390], "text": "Secondary", "label": "school_name", "id": 124, "words": [{"box": [343, 1362, 478, 1390], "text": "Secondary"}]}, {"box": [483, 1362, 571, 1390], "text": "School", "label": "school_name", "id": 125, "words": [{"box": [483, 1362, 571, 1390], "text": "School"}]}, {"box": [1199, 1362, 1264, 1390], "text": "2001", "label": "school_date", "id": 126, "words": [{"box": [1199, 1362, 1264, 1390], "text": "2001"}]}, {"box": [1269, 1362, 1294, 1390], "text": "to", "label": "school_date", "id": 127, "words": [{"box": [1269, 1362, 1294, 1390], "text": "to"}]}, {"box": [1300, 1362, 1364, 1390], "text": "2005", "label": "school_date", "id": 128, "words": [{"box": [1300, 1362, 1364, 1390], "text": "2005"}]}, {"box": [299, 1424, 362, 1452], "text": "GCE", "label": "grade", "id": 129, "words": [{"box": [299, 1424, 362, 1452], "text": "GCE"}]}, {"box": [367, 1424, 404, 1452], "text": "\u2018O\u2019", "label": "grade", "id": 130, "words": [{"box": [367, 1424, 404, 1452], "text": "\u2018O\u2019"}]}, {"box": [409, 1424, 478, 1452], "text": "Level", "label": "grade", "id": 131, "words": [{"box": [409, 1424, 478, 1452], "text": "Level"}]}, {"box": [299, 1485, 430, 1513], "text": "Distinction", "label": "other", "id": 132, "words": [{"box": [299, 1485, 430, 1513], "text": "Distinction"}]}, {"box": [435, 1485, 459, 1513], "text": "in", "label": "other", "id": 133, "words": [{"box": [435, 1485, 459, 1513], "text": "in"}]}, {"box": [464, 1485, 577, 1513], "text": "Chinese,", "label": "other", "id": 134, "words": [{"box": [464, 1485, 577, 1513], "text": "Chinese,"}]}, {"box": [582, 1485, 706, 1513], "text": "Additional", "label": "other", "id": 135, "words": [{"box": [582, 1485, 706, 1513], "text": "Additional"}]}, {"box": [711, 1485, 871, 1513], "text": "Mathematics", "label": "other", "id": 136, "words": [{"box": [711, 1485, 871, 1513], "text": "Mathematics"}]}, {"box": [876, 1485, 925, 1513], "text": "and", "label": "other", "id": 137, "words": [{"box": [876, 1485, 925, 1513], "text": "and"}]}, {"box": [930, 1485, 1073, 1513], "text": "Elementary", "label": "other", "id": 138, "words": [{"box": [930, 1485, 1073, 1513], "text": "Elementary"}]}, {"box": [1078, 1485, 1238, 1513], "text": "Mathematics", "label": "other", "id": 139, "words": [{"box": [1078, 1485, 1238, 1513], "text": "Mathematics"}]}, {"box": [200, 1545, 396, 1573], "text": "EMPOLYMENT", "label": "other", "id": 140, "words": [{"box": [200, 1545, 396, 1573], "text": "EMPOLYMENT"}]}, {"box": [200, 1610, 235, 1638], "text": "JP", "label": "company_name", "id": 141, "words": [{"box": [200, 1610, 235, 1638], "text": "JP"}]}, {"box": [240, 1610, 336, 1638], "text": "Morgan", "label": "company_name", "id": 142, "words": [{"box": [240, 1610, 336, 1638], "text": "Morgan"}]}, {"box": [341, 1610, 424, 1638], "text": "Chase", "label": "company_name", "id": 143, "words": [{"box": [341, 1610, 424, 1638], "text": "Chase"}]}, {"box": [1199, 1610, 1254, 1638], "text": "JAN", "label": "company_date", "id": 144, "words": [{"box": [1199, 1610, 1254, 1638], "text": "JAN"}]}, {"box": [1259, 1610, 1324, 1638], "text": "2016", "label": "company_date", "id": 145, "words": [{"box": [1259, 1610, 1324, 1638], "text": "2016"}]}, {"box": [1329, 1610, 1355, 1638], "text": "to", "label": "company_date", "id": 146, "words": [{"box": [1329, 1610, 1355, 1638], "text": "to"}]}, {"box": [1360, 1610, 1458, 1638], "text": "Present", "label": "company_date", "id": 147, "words": [{"box": [1360, 1610, 1458, 1638], "text": "Present"}]}, {"box": [200, 1670, 248, 1698], "text": "CIB", "label": "position", "id": 148, "words": [{"box": [200, 1670, 248, 1698], "text": "CIB"}]}, {"box": [253, 1670, 392, 1698], "text": "Operations", "label": "position", "id": 149, "words": [{"box": [253, 1670, 392, 1698], "text": "Operations"}]}, {"box": [397, 1670, 546, 1698], "text": "(Derivatives", "label": "position", "id": 150, "words": [{"box": [397, 1670, 546, 1698], "text": "(Derivatives"}]}, {"box": [551, 1670, 614, 1698], "text": "Ops)", "label": "position", "id": 151, "words": [{"box": [551, 1670, 614, 1698], "text": "Ops)"}]}, {"box": [619, 1670, 768, 1698], "text": "Settlements", "label": "position", "id": 152, "words": [{"box": [619, 1670, 768, 1698], "text": "Settlements"}]}, {"box": [773, 1670, 867, 1698], "text": "Analyst", "label": "position", "id": 153, "words": [{"box": [773, 1670, 867, 1698], "text": "Analyst"}]}, {"box": [274, 1730, 336, 1757], "text": "OTC", "label": "other", "id": 154, "words": [{"box": [274, 1730, 336, 1757], "text": "OTC"}]}, {"box": [341, 1730, 490, 1757], "text": "Settlements", "label": "other", "id": 155, "words": [{"box": [341, 1730, 490, 1757], "text": "Settlements"}]}, {"box": [495, 1730, 521, 1757], "text": "of", "label": "other", "id": 156, "words": [{"box": [495, 1730, 521, 1757], "text": "of"}]}, {"box": [526, 1730, 624, 1757], "text": "multiple", "label": "other", "id": 157, "words": [{"box": [526, 1730, 624, 1757], "text": "multiple"}]}, {"box": [629, 1730, 738, 1757], "text": "products", "label": "other", "id": 158, "words": [{"box": [629, 1730, 738, 1757], "text": "products"}]}, {"box": [743, 1730, 855, 1757], "text": "including", "label": "other", "id": 159, "words": [{"box": [743, 1730, 855, 1757], "text": "including"}]}, {"box": [860, 1730, 906, 1757], "text": "FX,", "label": "other", "id": 160, "words": [{"box": [860, 1730, 906, 1757], "text": "FX,"}]}, {"box": [911, 1730, 979, 1757], "text": "NDF,", "label": "other", "id": 161, "words": [{"box": [911, 1730, 979, 1757], "text": "NDF,"}]}, {"box": [984, 1730, 1051, 1757], "text": "FXO,", "label": "other", "id": 162, "words": [{"box": [984, 1730, 1051, 1757], "text": "FXO,"}]}, {"box": [1056, 1730, 1139, 1757], "text": "Rates,", "label": "other", "id": 163, "words": [{"box": [1056, 1730, 1139, 1757], "text": "Rates,"}]}, {"box": [1144, 1730, 1229, 1757], "text": "Credit,", "label": "other", "id": 164, "words": [{"box": [1144, 1730, 1229, 1757], "text": "Credit,"}]}, {"box": [1233, 1730, 1313, 1757], "text": "Equity", "label": "other", "id": 165, "words": [{"box": [1233, 1730, 1313, 1757], "text": "Equity"}]}, {"box": [1318, 1730, 1367, 1757], "text": "and", "label": "other", "id": 166, "words": [{"box": [1318, 1730, 1367, 1757], "text": "and"}]}, {"box": [299, 1762, 464, 1789], "text": "Commodities", "label": "other", "id": 167, "words": [{"box": [299, 1762, 464, 1789], "text": "Commodities"}]}, {"box": [469, 1762, 609, 1789], "text": "Derivatives", "label": "other", "id": 168, "words": [{"box": [469, 1762, 609, 1789], "text": "Derivatives"}]}, {"box": [274, 1821, 481, 1849], "text": "Pre-confirmation", "label": "other", "id": 169, "words": [{"box": [274, 1821, 481, 1849], "text": "Pre-confirmation"}]}, {"box": [486, 1821, 511, 1849], "text": "of", "label": "other", "id": 170, "words": [{"box": [486, 1821, 511, 1849], "text": "of"}]}, {"box": [516, 1821, 669, 1849], "text": "settlements,", "label": "other", "id": 171, "words": [{"box": [516, 1821, 669, 1849], "text": "settlements,"}]}, {"box": [674, 1821, 783, 1849], "text": "payment", "label": "other", "id": 172, "words": [{"box": [674, 1821, 783, 1849], "text": "payment"}]}, {"box": [788, 1821, 889, 1849], "text": "release,", "label": "other", "id": 173, "words": [{"box": [788, 1821, 889, 1849], "text": "release,"}]}, {"box": [894, 1821, 1056, 1849], "text": "maintenance", "label": "other", "id": 174, "words": [{"box": [894, 1821, 1056, 1849], "text": "maintenance"}]}, {"box": [1061, 1821, 1087, 1849], "text": "of", "label": "other", "id": 175, "words": [{"box": [1061, 1821, 1087, 1849], "text": "of"}]}, {"box": [1093, 1821, 1160, 1849], "text": "client", "label": "other", "id": 176, "words": [{"box": [1093, 1821, 1160, 1849], "text": "client"}]}, {"box": [1165, 1821, 1214, 1849], "text": "and", "label": "other", "id": 177, "words": [{"box": [1165, 1821, 1214, 1849], "text": "and"}]}, {"box": [1219, 1821, 1332, 1849], "text": "business", "label": "other", "id": 178, "words": [{"box": [1219, 1821, 1332, 1849], "text": "business"}]}, {"box": [1337, 1821, 1456, 1849], "text": "reference", "label": "other", "id": 179, "words": [{"box": [1337, 1821, 1456, 1849], "text": "reference"}]}, {"box": [299, 1853, 364, 1881], "text": "data,", "label": "other", "id": 180, "words": [{"box": [299, 1853, 364, 1881], "text": "data,"}]}, {"box": [369, 1853, 502, 1881], "text": "generation", "label": "other", "id": 181, "words": [{"box": [369, 1853, 502, 1881], "text": "generation"}]}, {"box": [508, 1853, 533, 1881], "text": "of", "label": "other", "id": 182, "words": [{"box": [508, 1853, 533, 1881], "text": "of"}]}, {"box": [538, 1853, 629, 1881], "text": "advice,", "label": "other", "id": 183, "words": [{"box": [538, 1853, 629, 1881], "text": "advice,"}]}, {"box": [634, 1853, 689, 1881], "text": "post", "label": "other", "id": 184, "words": [{"box": [634, 1853, 689, 1881], "text": "post"}]}, {"box": [694, 1853, 825, 1881], "text": "settlement", "label": "other", "id": 185, "words": [{"box": [694, 1853, 825, 1881], "text": "settlement"}]}, {"box": [830, 1853, 987, 1881], "text": "investigation", "label": "other", "id": 186, "words": [{"box": [830, 1853, 987, 1881], "text": "investigation"}]}, {"box": [992, 1853, 1041, 1881], "text": "and", "label": "other", "id": 187, "words": [{"box": [992, 1853, 1041, 1881], "text": "and"}]}, {"box": [1046, 1853, 1134, 1881], "text": "ad-hoc", "label": "other", "id": 188, "words": [{"box": [1046, 1853, 1134, 1881], "text": "ad-hoc"}]}, {"box": [1139, 1853, 1284, 1881], "text": "break/issue", "label": "other", "id": 189, "words": [{"box": [1139, 1853, 1284, 1881], "text": "break/issue"}]}, {"box": [1289, 1853, 1426, 1881], "text": "resolutions", "label": "other", "id": 190, "words": [{"box": [1289, 1853, 1426, 1881], "text": "resolutions"}]}, {"box": [274, 1913, 387, 1941], "text": "Ensuring", "label": "other", "id": 191, "words": [{"box": [274, 1913, 387, 1941], "text": "Ensuring"}]}, {"box": [391, 1913, 440, 1941], "text": "that", "label": "other", "id": 192, "words": [{"box": [391, 1913, 440, 1941], "text": "that"}]}, {"box": [446, 1913, 476, 1941], "text": "all", "label": "other", "id": 193, "words": [{"box": [446, 1913, 476, 1941], "text": "all"}]}, {"box": [481, 1913, 604, 1941], "text": "payments", "label": "other", "id": 194, "words": [{"box": [481, 1913, 604, 1941], "text": "payments"}]}, {"box": [609, 1913, 652, 1941], "text": "are", "label": "other", "id": 195, "words": [{"box": [609, 1913, 652, 1941], "text": "are"}]}, {"box": [657, 1913, 741, 1941], "text": "settled", "label": "other", "id": 196, "words": [{"box": [657, 1913, 741, 1941], "text": "settled"}]}, {"box": [746, 1913, 854, 1941], "text": "correctly", "label": "other", "id": 197, "words": [{"box": [746, 1913, 854, 1941], "text": "correctly"}]}, {"box": [859, 1913, 908, 1941], "text": "and", "label": "other", "id": 198, "words": [{"box": [859, 1913, 908, 1941], "text": "and"}]}, {"box": [913, 1913, 937, 1941], "text": "in", "label": "other", "id": 199, "words": [{"box": [913, 1913, 937, 1941], "text": "in"}]}, {"box": [942, 1913, 961, 1941], "text": "a", "label": "other", "id": 200, "words": [{"box": [942, 1913, 961, 1941], "text": "a"}]}, {"box": [965, 1913, 1040, 1941], "text": "timely", "label": "other", "id": 201, "words": [{"box": [965, 1913, 1040, 1941], "text": "timely"}]}, {"box": [1046, 1913, 1150, 1941], "text": "manner.", "label": "other", "id": 202, "words": [{"box": [1046, 1913, 1150, 1941], "text": "manner."}]}, {"box": [274, 1973, 399, 2000], "text": "Resolving", "label": "other", "id": 203, "words": [{"box": [274, 1973, 399, 2000], "text": "Resolving"}]}, {"box": [404, 1973, 451, 2000], "text": "any", "label": "other", "id": 204, "words": [{"box": [404, 1973, 451, 2000], "text": "any"}]}, {"box": [456, 1973, 603, 2000], "text": "outstanding", "label": "other", "id": 205, "words": [{"box": [456, 1973, 603, 2000], "text": "outstanding"}]}, {"box": [608, 1973, 694, 2000], "text": "breaks", "label": "other", "id": 206, "words": [{"box": [608, 1973, 694, 2000], "text": "breaks"}]}, {"box": [699, 1973, 723, 2000], "text": "in", "label": "other", "id": 207, "words": [{"box": [699, 1973, 723, 2000], "text": "in"}]}, {"box": [728, 1973, 808, 2000], "text": "nostro", "label": "other", "id": 208, "words": [{"box": [728, 1973, 808, 2000], "text": "nostro"}]}, {"box": [813, 1973, 934, 2000], "text": "accounts.", "label": "other", "id": 209, "words": [{"box": [813, 1973, 934, 2000], "text": "accounts."}]}, {"box": [274, 2033, 404, 2060], "text": "Identifying", "label": "other", "id": 210, "words": [{"box": [274, 2033, 404, 2060], "text": "Identifying"}]}, {"box": [408, 2033, 458, 2060], "text": "and", "label": "other", "id": 211, "words": [{"box": [408, 2033, 458, 2060], "text": "and"}]}, {"box": [463, 2033, 620, 2060], "text": "investigating", "label": "other", "id": 212, "words": [{"box": [463, 2033, 620, 2060], "text": "investigating"}]}, {"box": [624, 2033, 672, 2060], "text": "any", "label": "other", "id": 213, "words": [{"box": [624, 2033, 672, 2060], "text": "any"}]}, {"box": [677, 2033, 727, 2060], "text": "root", "label": "other", "id": 214, "words": [{"box": [677, 2033, 727, 2060], "text": "root"}]}, {"box": [732, 2033, 817, 2060], "text": "cause.", "label": "other", "id": 215, "words": [{"box": [732, 2033, 817, 2060], "text": "cause."}]}, {"box": [274, 2092, 458, 2120], "text": "Establishingan", "label": "other", "id": 216, "words": [{"box": [274, 2092, 458, 2120], "text": "Establishingan"}]}, {"box": [463, 2092, 575, 2120], "text": "excellent", "label": "other", "id": 217, "words": [{"box": [463, 2092, 575, 2120], "text": "excellent"}]}, {"box": [580, 2092, 724, 2120], "text": "relationship", "label": "other", "id": 218, "words": [{"box": [580, 2092, 724, 2120], "text": "relationship"}]}, {"box": [729, 2092, 781, 2120], "text": "with", "label": "other", "id": 219, "words": [{"box": [729, 2092, 781, 2120], "text": "with"}]}, {"box": [786, 2092, 843, 2120], "text": "both", "label": "other", "id": 220, "words": [{"box": [786, 2092, 843, 2120], "text": "both"}]}, {"box": [848, 2092, 942, 2120], "text": "internal", "label": "other", "id": 221, "words": [{"box": [848, 2092, 942, 2120], "text": "internal"}]}, {"box": [947, 2092, 996, 2120], "text": "and", "label": "other", "id": 222, "words": [{"box": [947, 2092, 996, 2120], "text": "and"}]}, {"box": [1001, 2092, 1102, 2120], "text": "external", "label": "other", "id": 223, "words": [{"box": [1001, 2092, 1102, 2120], "text": "external"}]}, {"box": [1107, 2092, 1188, 2120], "text": "clients", "label": "other", "id": 224, "words": [{"box": [1107, 2092, 1188, 2120], "text": "clients"}]}]}