{"form": [{"box": [1326, 2214, 1343, 2241], "text": "4", "label": "other", "id": 0, "words": [{"box": [1326, 2214, 1343, 2241], "text": "4"}]}, {"box": [1346, 2214, 1362, 2241], "text": "|", "label": "other", "id": 1, "words": [{"box": [1346, 2214, 1362, 2241], "text": "|"}]}, {"box": [1365, 2214, 1447, 2241], "text": "Page", "label": "other", "id": 2, "words": [{"box": [1365, 2214, 1447, 2241], "text": "Page"}]}, {"box": [200, 245, 358, 276], "text": "EXECUTIVE", "label": "position", "id": 3, "words": [{"box": [200, 245, 358, 276], "text": "EXECUTIVE"}]}, {"box": [366, 245, 530, 276], "text": "SECRETARY", "label": "position", "id": 4, "words": [{"box": [366, 245, 530, 276], "text": "SECRETARY"}]}, {"box": [538, 245, 557, 276], "text": "\u2013", "label": "position", "id": 5, "words": [{"box": [538, 245, 557, 276], "text": "\u2013"}]}, {"box": [565, 245, 733, 276], "text": "REPORTING", "label": "position", "id": 6, "words": [{"box": [565, 245, 733, 276], "text": "REPORTING"}]}, {"box": [741, 245, 782, 276], "text": "TO", "label": "position", "id": 7, "words": [{"box": [741, 245, 782, 276], "text": "TO"}]}, {"box": [790, 245, 809, 276], "text": "2", "label": "position", "id": 8, "words": [{"box": [790, 245, 809, 276], "text": "2"}]}, {"box": [817, 245, 925, 276], "text": "SENIOR", "label": "position", "id": 9, "words": [{"box": [817, 245, 925, 276], "text": "SENIOR"}]}, {"box": [933, 245, 989, 276], "text": "VPS", "label": "position", "id": 10, "words": [{"box": [933, 245, 989, 276], "text": "VPS"}]}, {"box": [997, 245, 1014, 276], "text": "|", "label": "other", "id": 11, "words": [{"box": [997, 245, 1014, 276], "text": "|"}]}, {"box": [1023, 245, 1092, 276], "text": "MAR", "label": "company_date", "id": 12, "words": [{"box": [1023, 245, 1092, 276], "text": "MAR"}]}, {"box": [1101, 245, 1172, 276], "text": "2008", "label": "company_date", "id": 13, "words": [{"box": [1101, 245, 1172, 276], "text": "2008"}]}, {"box": [1181, 245, 1199, 276], "text": "\u2013", "label": "company_date", "id": 14, "words": [{"box": [1181, 245, 1199, 276], "text": "\u2013"}]}, {"box": [1207, 245, 1276, 276], "text": "MAR", "label": "company_date", "id": 15, "words": [{"box": [1207, 245, 1276, 276], "text": "MAR"}]}, {"box": [1284, 245, 1356, 276], "text": "2013", "label": "company_date", "id": 16, "words": [{"box": [1284, 245, 1356, 276], "text": "2013"}]}, {"box": [200, 302, 247, 333], "text": "AIG", "label": "company_name", "id": 17, "words": [{"box": [200, 302, 247, 333], "text": "AIG"}]}, {"box": [251, 302, 321, 333], "text": "APAC", "label": "company_name", "id": 18, "words": [{"box": [251, 302, 321, 333], "text": "APAC"}]}, {"box": [325, 302, 436, 333], "text": "Holdings", "label": "company_name", "id": 19, "words": [{"box": [325, 302, 436, 333], "text": "Holdings"}]}, {"box": [440, 302, 491, 333], "text": "Pte.", "label": "company_name", "id": 20, "words": [{"box": [440, 302, 491, 333], "text": "Pte."}]}, {"box": [495, 302, 544, 333], "text": "Ltd.", "label": "company_name", "id": 21, "words": [{"box": [495, 302, 544, 333], "text": "Ltd."}]}, {"box": [239, 404, 310, 435], "text": "From", "label": "other", "id": 22, "words": [{"box": [239, 404, 310, 435], "text": "From"}]}, {"box": [314, 404, 417, 435], "text": "January", "label": "other", "id": 23, "words": [{"box": [314, 404, 417, 435], "text": "January"}]}, {"box": [422, 404, 490, 435], "text": "2010", "label": "other", "id": 24, "words": [{"box": [422, 404, 490, 435], "text": "2010"}]}, {"box": [494, 404, 525, 435], "text": "to", "label": "other", "id": 25, "words": [{"box": [494, 404, 525, 435], "text": "to"}]}, {"box": [529, 404, 586, 435], "text": "Mar", "label": "other", "id": 26, "words": [{"box": [529, 404, 586, 435], "text": "Mar"}]}, {"box": [589, 404, 657, 435], "text": "2013", "label": "other", "id": 27, "words": [{"box": [589, 404, 657, 435], "text": "2013"}]}, {"box": [239, 443, 360, 474], "text": "Manages", "label": "other", "id": 28, "words": [{"box": [239, 443, 360, 474], "text": "Manages"}]}, {"box": [363, 443, 415, 474], "text": "and", "label": "other", "id": 29, "words": [{"box": [363, 443, 415, 474], "text": "and"}]}, {"box": [419, 443, 549, 474], "text": "maintains", "label": "other", "id": 30, "words": [{"box": [419, 443, 549, 474], "text": "maintains"}]}, {"box": [553, 443, 639, 474], "text": "Senior", "label": "other", "id": 31, "words": [{"box": [553, 443, 639, 474], "text": "Senior"}]}, {"box": [642, 443, 700, 474], "text": "VP\u2019s", "label": "other", "id": 32, "words": [{"box": [642, 443, 700, 474], "text": "VP\u2019s"}]}, {"box": [704, 443, 840, 474], "text": "calendars,", "label": "other", "id": 33, "words": [{"box": [704, 443, 840, 474], "text": "calendars,"}]}, {"box": [843, 443, 962, 474], "text": "schedule", "label": "other", "id": 34, "words": [{"box": [843, 443, 962, 474], "text": "schedule"}]}, {"box": [965, 443, 1158, 474], "text": "appointments,", "label": "other", "id": 35, "words": [{"box": [965, 443, 1158, 474], "text": "appointments,"}]}, {"box": [1162, 443, 1319, 474], "text": "coordinates", "label": "other", "id": 36, "words": [{"box": [1162, 443, 1319, 474], "text": "coordinates"}]}, {"box": [1327, 443, 1440, 474], "text": "complex", "label": "other", "id": 37, "words": [{"box": [1327, 443, 1440, 474], "text": "complex"}]}, {"box": [239, 482, 369, 513], "text": "meetings,", "label": "other", "id": 38, "words": [{"box": [239, 482, 369, 513], "text": "meetings,"}]}, {"box": [374, 482, 448, 513], "text": "video", "label": "other", "id": 39, "words": [{"box": [374, 482, 448, 513], "text": "video"}]}, {"box": [452, 482, 477, 513], "text": "&", "label": "other", "id": 40, "words": [{"box": [452, 482, 477, 513], "text": "&"}]}, {"box": [481, 482, 630, 513], "text": "conference", "label": "other", "id": 41, "words": [{"box": [481, 482, 630, 513], "text": "conference"}]}, {"box": [635, 482, 694, 513], "text": "calls", "label": "other", "id": 42, "words": [{"box": [635, 482, 694, 513], "text": "calls"}]}, {"box": [698, 482, 783, 513], "text": "across", "label": "other", "id": 43, "words": [{"box": [698, 482, 783, 513], "text": "across"}]}, {"box": [787, 482, 918, 513], "text": "Americas,", "label": "other", "id": 44, "words": [{"box": [787, 482, 918, 513], "text": "Americas,"}]}, {"box": [922, 482, 1026, 513], "text": "Europe,", "label": "other", "id": 45, "words": [{"box": [922, 482, 1026, 513], "text": "Europe,"}]}, {"box": [1030, 482, 1184, 513], "text": "Australasia,", "label": "other", "id": 46, "words": [{"box": [1030, 482, 1184, 513], "text": "Australasia,"}]}, {"box": [1189, 482, 1245, 513], "text": "Asia", "label": "other", "id": 47, "words": [{"box": [1189, 482, 1245, 513], "text": "Asia"}]}, {"box": [1250, 482, 1336, 513], "text": "Pacific", "label": "other", "id": 48, "words": [{"box": [1250, 482, 1336, 513], "text": "Pacific"}]}, {"box": [1340, 482, 1392, 513], "text": "and", "label": "other", "id": 49, "words": [{"box": [1340, 482, 1392, 513], "text": "and"}]}, {"box": [1396, 482, 1440, 513], "text": "Far", "label": "other", "id": 50, "words": [{"box": [1396, 482, 1440, 513], "text": "Far"}]}, {"box": [239, 521, 296, 551], "text": "East", "label": "other", "id": 51, "words": [{"box": [239, 521, 296, 551], "text": "East"}]}, {"box": [300, 521, 407, 551], "text": "regions.", "label": "other", "id": 52, "words": [{"box": [300, 521, 407, 551], "text": "regions."}]}, {"box": [239, 638, 361, 669], "text": "Performs", "label": "other", "id": 53, "words": [{"box": [239, 638, 361, 669], "text": "Performs"}]}, {"box": [366, 638, 505, 669], "text": "secretarial", "label": "other", "id": 54, "words": [{"box": [366, 638, 505, 669], "text": "secretarial"}]}, {"box": [509, 638, 593, 669], "text": "duties", "label": "other", "id": 55, "words": [{"box": [509, 638, 593, 669], "text": "duties"}]}, {"box": [597, 638, 638, 669], "text": "for", "label": "other", "id": 56, "words": [{"box": [597, 638, 638, 669], "text": "for"}]}, {"box": [643, 638, 717, 669], "text": "other", "label": "other", "id": 57, "words": [{"box": [643, 638, 717, 669], "text": "other"}]}, {"box": [722, 638, 785, 669], "text": "busy", "label": "other", "id": 58, "words": [{"box": [722, 638, 785, 669], "text": "busy"}]}, {"box": [790, 638, 860, 669], "text": "team", "label": "other", "id": 59, "words": [{"box": [790, 638, 860, 669], "text": "team"}]}, {"box": [865, 638, 991, 669], "text": "members", "label": "other", "id": 60, "words": [{"box": [865, 638, 991, 669], "text": "members"}]}, {"box": [996, 638, 1065, 669], "text": "(VPs)", "label": "other", "id": 61, "words": [{"box": [996, 638, 1065, 669], "text": "(VPs)"}]}, {"box": [1070, 638, 1097, 669], "text": "in", "label": "other", "id": 62, "words": [{"box": [1070, 638, 1097, 669], "text": "in"}]}, {"box": [1101, 638, 1119, 669], "text": "a", "label": "other", "id": 63, "words": [{"box": [1101, 638, 1119, 669], "text": "a"}]}, {"box": [1124, 638, 1263, 669], "text": "fast-paced", "label": "other", "id": 64, "words": [{"box": [1124, 638, 1263, 669], "text": "fast-paced"}]}, {"box": [1268, 638, 1439, 669], "text": "environment", "label": "other", "id": 65, "words": [{"box": [1268, 638, 1439, 669], "text": "environment"}]}, {"box": [239, 677, 369, 708], "text": "(including", "label": "other", "id": 66, "words": [{"box": [239, 677, 369, 708], "text": "(including"}]}, {"box": [380, 677, 550, 708], "text": "coordination", "label": "other", "id": 67, "words": [{"box": [380, 677, 550, 708], "text": "coordination"}]}, {"box": [561, 677, 591, 708], "text": "of", "label": "other", "id": 68, "words": [{"box": [561, 677, 591, 708], "text": "of"}]}, {"box": [602, 677, 695, 708], "text": "logistic", "label": "other", "id": 69, "words": [{"box": [602, 677, 695, 708], "text": "logistic"}]}, {"box": [707, 677, 787, 708], "text": "needs", "label": "other", "id": 70, "words": [{"box": [707, 677, 787, 708], "text": "needs"}]}, {"box": [799, 677, 839, 708], "text": "for", "label": "other", "id": 71, "words": [{"box": [799, 677, 839, 708], "text": "for"}]}, {"box": [850, 677, 965, 708], "text": "business", "label": "other", "id": 72, "words": [{"box": [850, 677, 965, 708], "text": "business"}]}, {"box": [976, 677, 1045, 708], "text": "trips,", "label": "other", "id": 73, "words": [{"box": [976, 677, 1045, 708], "text": "trips,"}]}, {"box": [1056, 677, 1183, 708], "text": "arranging", "label": "other", "id": 74, "words": [{"box": [1056, 677, 1183, 708], "text": "arranging"}]}, {"box": [1194, 677, 1307, 708], "text": "complex", "label": "other", "id": 75, "words": [{"box": [1194, 677, 1307, 708], "text": "complex"}]}, {"box": [1329, 677, 1439, 708], "text": "meeting", "label": "other", "id": 76, "words": [{"box": [1329, 677, 1439, 708], "text": "meeting"}]}, {"box": [239, 716, 370, 746], "text": "schedules", "label": "other", "id": 77, "words": [{"box": [239, 716, 370, 746], "text": "schedules"}]}, {"box": [374, 716, 459, 746], "text": "across", "label": "other", "id": 78, "words": [{"box": [374, 716, 459, 746], "text": "across"}]}, {"box": [463, 716, 519, 746], "text": "Asia", "label": "other", "id": 79, "words": [{"box": [463, 716, 519, 746], "text": "Asia"}]}, {"box": [523, 716, 609, 746], "text": "Pacific", "label": "other", "id": 80, "words": [{"box": [523, 716, 609, 746], "text": "Pacific"}]}, {"box": [613, 716, 638, 746], "text": "&", "label": "other", "id": 81, "words": [{"box": [613, 716, 638, 746], "text": "&"}]}, {"box": [642, 716, 686, 746], "text": "Far", "label": "other", "id": 82, "words": [{"box": [642, 716, 686, 746], "text": "Far"}]}, {"box": [689, 716, 747, 746], "text": "East", "label": "other", "id": 83, "words": [{"box": [689, 716, 747, 746], "text": "East"}]}, {"box": [750, 716, 849, 746], "text": "regions", "label": "other", "id": 84, "words": [{"box": [750, 716, 849, 746], "text": "regions"}]}, {"box": [853, 716, 893, 746], "text": "for", "label": "other", "id": 85, "words": [{"box": [853, 716, 893, 746], "text": "for"}]}, {"box": [897, 716, 971, 746], "text": "video", "label": "other", "id": 86, "words": [{"box": [897, 716, 971, 746], "text": "video"}]}, {"box": [975, 716, 1027, 746], "text": "and", "label": "other", "id": 87, "words": [{"box": [975, 716, 1027, 746], "text": "and"}]}, {"box": [1031, 716, 1260, 746], "text": "teleconferences).", "label": "other", "id": 88, "words": [{"box": [1031, 716, 1260, 746], "text": "teleconferences)."}]}, {"box": [239, 795, 396, 825], "text": "Preparation", "label": "other", "id": 89, "words": [{"box": [239, 795, 396, 825], "text": "Preparation"}]}, {"box": [399, 795, 424, 825], "text": "&", "label": "other", "id": 90, "words": [{"box": [399, 795, 424, 825], "text": "&"}]}, {"box": [427, 795, 575, 825], "text": "submission", "label": "other", "id": 91, "words": [{"box": [427, 795, 575, 825], "text": "submission"}]}, {"box": [579, 795, 609, 825], "text": "of", "label": "other", "id": 92, "words": [{"box": [579, 795, 609, 825], "text": "of"}]}, {"box": [612, 795, 645, 825], "text": "all", "label": "other", "id": 93, "words": [{"box": [612, 795, 645, 825], "text": "all"}]}, {"box": [648, 795, 866, 825], "text": "business-related", "label": "other", "id": 94, "words": [{"box": [648, 795, 866, 825], "text": "business-related"}]}, {"box": [869, 795, 992, 825], "text": "expenses", "label": "other", "id": 95, "words": [{"box": [869, 795, 992, 825], "text": "expenses"}]}, {"box": [996, 795, 1081, 825], "text": "claims", "label": "other", "id": 96, "words": [{"box": [996, 795, 1081, 825], "text": "claims"}]}, {"box": [1084, 795, 1191, 825], "text": "through", "label": "other", "id": 97, "words": [{"box": [1084, 795, 1191, 825], "text": "through"}]}, {"box": [1194, 795, 1286, 825], "text": "concur", "label": "other", "id": 98, "words": [{"box": [1194, 795, 1286, 825], "text": "concur"}]}, {"box": [1289, 795, 1392, 825], "text": "system.", "label": "other", "id": 99, "words": [{"box": [1289, 795, 1392, 825], "text": "system."}]}, {"box": [239, 871, 330, 902], "text": "Ensure", "label": "other", "id": 100, "words": [{"box": [239, 871, 330, 902], "text": "Ensure"}]}, {"box": [334, 871, 419, 902], "text": "timely", "label": "other", "id": 101, "words": [{"box": [334, 871, 419, 902], "text": "timely"}]}, {"box": [423, 871, 571, 902], "text": "submission", "label": "other", "id": 102, "words": [{"box": [423, 871, 571, 902], "text": "submission"}]}, {"box": [575, 871, 605, 902], "text": "of", "label": "other", "id": 103, "words": [{"box": [575, 871, 605, 902], "text": "of"}]}, {"box": [609, 871, 706, 902], "text": "reports", "label": "other", "id": 104, "words": [{"box": [609, 871, 706, 902], "text": "reports"}]}, {"box": [711, 871, 777, 902], "text": "from", "label": "other", "id": 105, "words": [{"box": [711, 871, 777, 902], "text": "from"}]}, {"box": [781, 871, 844, 902], "text": "local", "label": "other", "id": 106, "words": [{"box": [781, 871, 844, 902], "text": "local"}]}, {"box": [848, 871, 937, 902], "text": "offices", "label": "other", "id": 107, "words": [{"box": [848, 871, 937, 902], "text": "offices"}]}, {"box": [941, 871, 1026, 902], "text": "across", "label": "other", "id": 108, "words": [{"box": [941, 871, 1026, 902], "text": "across"}]}, {"box": [1030, 871, 1087, 902], "text": "Asia", "label": "other", "id": 109, "words": [{"box": [1030, 871, 1087, 902], "text": "Asia"}]}, {"box": [1091, 871, 1177, 902], "text": "Pacific", "label": "other", "id": 110, "words": [{"box": [1091, 871, 1177, 902], "text": "Pacific"}]}, {"box": [1181, 871, 1206, 902], "text": "&", "label": "other", "id": 111, "words": [{"box": [1181, 871, 1206, 902], "text": "&"}]}, {"box": [1210, 871, 1254, 902], "text": "Far", "label": "other", "id": 112, "words": [{"box": [1210, 871, 1254, 902], "text": "Far"}]}, {"box": [1257, 871, 1314, 902], "text": "East", "label": "other", "id": 113, "words": [{"box": [1257, 871, 1314, 902], "text": "East"}]}, {"box": [1318, 871, 1425, 902], "text": "regions.", "label": "other", "id": 114, "words": [{"box": [1318, 871, 1425, 902], "text": "regions."}]}, {"box": [239, 950, 348, 981], "text": "Compile", "label": "other", "id": 115, "words": [{"box": [239, 950, 348, 981], "text": "Compile"}]}, {"box": [353, 950, 399, 981], "text": "the", "label": "other", "id": 116, "words": [{"box": [353, 950, 399, 981], "text": "the"}]}, {"box": [404, 950, 510, 981], "text": "reports,", "label": "other", "id": 117, "words": [{"box": [404, 950, 510, 981], "text": "reports,"}]}, {"box": [514, 950, 632, 981], "text": "analysed", "label": "other", "id": 118, "words": [{"box": [514, 950, 632, 981], "text": "analysed"}]}, {"box": [637, 950, 688, 981], "text": "and", "label": "other", "id": 119, "words": [{"box": [637, 950, 688, 981], "text": "and"}]}, {"box": [693, 950, 841, 981], "text": "submission", "label": "other", "id": 120, "words": [{"box": [693, 950, 841, 981], "text": "submission"}]}, {"box": [845, 950, 876, 981], "text": "to", "label": "other", "id": 121, "words": [{"box": [845, 950, 876, 981], "text": "to"}]}, {"box": [880, 950, 924, 981], "text": "HQ", "label": "other", "id": 122, "words": [{"box": [880, 950, 924, 981], "text": "HQ"}]}, {"box": [929, 950, 1001, 981], "text": "(New", "label": "other", "id": 123, "words": [{"box": [929, 950, 1001, 981], "text": "(New"}]}, {"box": [1002, 950, 1081, 981], "text": "York).", "label": "other", "id": 124, "words": [{"box": [1002, 950, 1081, 981], "text": "York)."}]}, {"box": [239, 1029, 346, 1060], "text": "Handles", "label": "other", "id": 125, "words": [{"box": [239, 1029, 346, 1060], "text": "Handles"}]}, {"box": [350, 1029, 396, 1060], "text": "the", "label": "other", "id": 126, "words": [{"box": [350, 1029, 396, 1060], "text": "the"}]}, {"box": [399, 1029, 527, 1060], "text": "inventory", "label": "other", "id": 127, "words": [{"box": [399, 1029, 527, 1060], "text": "inventory"}]}, {"box": [531, 1029, 583, 1060], "text": "and", "label": "other", "id": 128, "words": [{"box": [531, 1029, 583, 1060], "text": "and"}]}, {"box": [586, 1029, 729, 1060], "text": "requisition", "label": "other", "id": 129, "words": [{"box": [586, 1029, 729, 1060], "text": "requisition"}]}, {"box": [733, 1029, 762, 1060], "text": "of", "label": "other", "id": 130, "words": [{"box": [733, 1029, 762, 1060], "text": "of"}]}, {"box": [766, 1029, 842, 1060], "text": "office", "label": "other", "id": 131, "words": [{"box": [766, 1029, 842, 1060], "text": "office"}]}, {"box": [846, 1029, 955, 1060], "text": "supplies", "label": "other", "id": 132, "words": [{"box": [846, 1029, 955, 1060], "text": "supplies"}]}, {"box": [958, 1029, 999, 1060], "text": "for", "label": "other", "id": 133, "words": [{"box": [958, 1029, 999, 1060], "text": "for"}]}, {"box": [1002, 1029, 1100, 1060], "text": "various", "label": "other", "id": 134, "words": [{"box": [1002, 1029, 1100, 1060], "text": "various"}]}, {"box": [1103, 1029, 1283, 1060], "text": "departments.", "label": "other", "id": 135, "words": [{"box": [1103, 1029, 1283, 1060], "text": "departments."}]}, {"box": [239, 1105, 399, 1136], "text": "Coordinates", "label": "other", "id": 136, "words": [{"box": [239, 1105, 399, 1136], "text": "Coordinates"}]}, {"box": [411, 1105, 463, 1136], "text": "and", "label": "other", "id": 137, "words": [{"box": [411, 1105, 463, 1136], "text": "and"}]}, {"box": [475, 1105, 561, 1136], "text": "set-up", "label": "other", "id": 138, "words": [{"box": [475, 1105, 561, 1136], "text": "set-up"}]}, {"box": [573, 1105, 602, 1136], "text": "of", "label": "other", "id": 139, "words": [{"box": [573, 1105, 602, 1136], "text": "of"}]}, {"box": [614, 1105, 687, 1136], "text": "APAC", "label": "other", "id": 140, "words": [{"box": [614, 1105, 687, 1136], "text": "APAC"}]}, {"box": [700, 1105, 724, 1136], "text": "&", "label": "other", "id": 141, "words": [{"box": [700, 1105, 724, 1136], "text": "&"}]}, {"box": [737, 1105, 780, 1136], "text": "Far", "label": "other", "id": 142, "words": [{"box": [737, 1105, 780, 1136], "text": "Far"}]}, {"box": [793, 1105, 850, 1136], "text": "East", "label": "other", "id": 143, "words": [{"box": [793, 1105, 850, 1136], "text": "East"}]}, {"box": [862, 1105, 1014, 1136], "text": "Conference", "label": "other", "id": 144, "words": [{"box": [862, 1105, 1014, 1136], "text": "Conference"}]}, {"box": [1026, 1105, 1078, 1136], "text": "and", "label": "other", "id": 145, "words": [{"box": [1026, 1105, 1078, 1136], "text": "and"}]}, {"box": [1090, 1105, 1210, 1136], "text": "seminars", "label": "other", "id": 146, "words": [{"box": [1090, 1105, 1210, 1136], "text": "seminars"}]}, {"box": [1222, 1105, 1297, 1136], "text": "every", "label": "other", "id": 147, "words": [{"box": [1222, 1105, 1297, 1136], "text": "every"}]}, {"box": [1309, 1105, 1439, 1136], "text": "quarterly.", "label": "other", "id": 148, "words": [{"box": [1309, 1105, 1439, 1136], "text": "quarterly."}]}, {"box": [239, 1144, 397, 1175], "text": "(submission", "label": "other", "id": 149, "words": [{"box": [239, 1144, 397, 1175], "text": "(submission"}]}, {"box": [407, 1144, 448, 1175], "text": "for", "label": "other", "id": 150, "words": [{"box": [407, 1144, 448, 1175], "text": "for"}]}, {"box": [459, 1144, 576, 1175], "text": "approval", "label": "other", "id": 151, "words": [{"box": [459, 1144, 576, 1175], "text": "approval"}]}, {"box": [587, 1144, 694, 1175], "text": "through", "label": "other", "id": 152, "words": [{"box": [587, 1144, 694, 1175], "text": "through"}]}, {"box": [702, 1144, 812, 1175], "text": "star-cite", "label": "other", "id": 153, "words": [{"box": [702, 1144, 812, 1175], "text": "star-cite"}]}, {"box": [821, 1144, 916, 1175], "text": "system", "label": "other", "id": 154, "words": [{"box": [821, 1144, 916, 1175], "text": "system"}]}, {"box": [924, 1144, 965, 1175], "text": "for", "label": "other", "id": 155, "words": [{"box": [924, 1144, 965, 1175], "text": "for"}]}, {"box": [974, 1144, 1076, 1175], "text": "budget,", "label": "other", "id": 156, "words": [{"box": [974, 1144, 1076, 1175], "text": "budget,"}]}, {"box": [1085, 1144, 1198, 1175], "text": "sourcing", "label": "other", "id": 157, "words": [{"box": [1085, 1144, 1198, 1175], "text": "sourcing"}]}, {"box": [1207, 1144, 1259, 1175], "text": "and", "label": "other", "id": 158, "words": [{"box": [1207, 1144, 1259, 1175], "text": "and"}]}, {"box": [1268, 1144, 1401, 1175], "text": "proposing", "label": "other", "id": 159, "words": [{"box": [1268, 1144, 1401, 1175], "text": "proposing"}]}, {"box": [1410, 1144, 1440, 1175], "text": "of", "label": "other", "id": 160, "words": [{"box": [1410, 1144, 1440, 1175], "text": "of"}]}, {"box": [239, 1183, 347, 1213], "text": "location", "label": "other", "id": 161, "words": [{"box": [239, 1183, 347, 1213], "text": "location"}]}, {"box": [351, 1183, 391, 1213], "text": "for", "label": "other", "id": 162, "words": [{"box": [351, 1183, 391, 1213], "text": "for"}]}, {"box": [395, 1183, 458, 1213], "text": "local", "label": "other", "id": 163, "words": [{"box": [395, 1183, 458, 1213], "text": "local"}]}, {"box": [462, 1183, 493, 1213], "text": "or", "label": "other", "id": 164, "words": [{"box": [462, 1183, 493, 1213], "text": "or"}]}, {"box": [497, 1183, 614, 1213], "text": "overseas", "label": "other", "id": 165, "words": [{"box": [497, 1183, 614, 1213], "text": "overseas"}]}, {"box": [618, 1183, 715, 1213], "text": "events,", "label": "other", "id": 166, "words": [{"box": [618, 1183, 715, 1213], "text": "events,"}]}, {"box": [719, 1183, 867, 1213], "text": "submission", "label": "other", "id": 167, "words": [{"box": [719, 1183, 867, 1213], "text": "submission"}]}, {"box": [870, 1183, 900, 1213], "text": "of", "label": "other", "id": 168, "words": [{"box": [870, 1183, 900, 1213], "text": "of"}]}, {"box": [903, 1183, 1047, 1213], "text": "post-event", "label": "other", "id": 169, "words": [{"box": [903, 1183, 1047, 1213], "text": "post-event"}]}, {"box": [1051, 1183, 1191, 1213], "text": "evaluation", "label": "other", "id": 170, "words": [{"box": [1051, 1183, 1191, 1213], "text": "evaluation"}]}, {"box": [1194, 1183, 1265, 1213], "text": "input", "label": "other", "id": 171, "words": [{"box": [1194, 1183, 1265, 1213], "text": "input"}]}, {"box": [1269, 1183, 1294, 1213], "text": "&", "label": "other", "id": 172, "words": [{"box": [1269, 1183, 1294, 1213], "text": "&"}]}, {"box": [1298, 1183, 1440, 1213], "text": "summary).", "label": "other", "id": 173, "words": [{"box": [1298, 1183, 1440, 1213], "text": "summary)."}]}, {"box": [239, 1260, 367, 1291], "text": "Reporting", "label": "other", "id": 174, "words": [{"box": [239, 1260, 367, 1291], "text": "Reporting"}]}, {"box": [371, 1260, 401, 1291], "text": "to", "label": "other", "id": 175, "words": [{"box": [371, 1260, 401, 1291], "text": "to"}]}, {"box": [405, 1260, 474, 1291], "text": "Head", "label": "other", "id": 176, "words": [{"box": [405, 1260, 474, 1291], "text": "Head"}]}, {"box": [478, 1260, 507, 1291], "text": "of", "label": "other", "id": 177, "words": [{"box": [478, 1260, 507, 1291], "text": "of"}]}, {"box": [511, 1260, 623, 1291], "text": "Regional", "label": "other", "id": 178, "words": [{"box": [511, 1260, 623, 1291], "text": "Regional"}]}, {"box": [628, 1260, 675, 1291], "text": "HR,", "label": "other", "id": 179, "words": [{"box": [628, 1260, 675, 1291], "text": "HR,"}]}, {"box": [679, 1260, 820, 1291], "text": "supporting", "label": "other", "id": 180, "words": [{"box": [679, 1260, 820, 1291], "text": "supporting"}]}, {"box": [824, 1260, 842, 1291], "text": "a", "label": "other", "id": 181, "words": [{"box": [824, 1260, 842, 1291], "text": "a"}]}, {"box": [846, 1260, 914, 1291], "text": "team", "label": "other", "id": 182, "words": [{"box": [846, 1260, 914, 1291], "text": "team"}]}, {"box": [919, 1260, 947, 1291], "text": "of", "label": "other", "id": 183, "words": [{"box": [919, 1260, 947, 1291], "text": "of"}]}, {"box": [952, 1260, 1032, 1291], "text": "13VPs", "label": "other", "id": 184, "words": [{"box": [952, 1260, 1032, 1291], "text": "13VPs"}]}, {"box": [239, 1299, 310, 1329], "text": "From", "label": "other", "id": 185, "words": [{"box": [239, 1299, 310, 1329], "text": "From"}]}, {"box": [314, 1299, 371, 1329], "text": "Mar", "label": "other", "id": 186, "words": [{"box": [314, 1299, 371, 1329], "text": "Mar"}]}, {"box": [375, 1299, 443, 1329], "text": "2008", "label": "other", "id": 187, "words": [{"box": [375, 1299, 443, 1329], "text": "2008"}]}, {"box": [448, 1299, 478, 1329], "text": "to", "label": "other", "id": 188, "words": [{"box": [448, 1299, 478, 1329], "text": "to"}]}, {"box": [483, 1299, 535, 1329], "text": "Dec", "label": "other", "id": 189, "words": [{"box": [483, 1299, 535, 1329], "text": "Dec"}]}, {"box": [539, 1299, 606, 1329], "text": "2009", "label": "other", "id": 190, "words": [{"box": [539, 1299, 606, 1329], "text": "2009"}]}, {"box": [239, 1375, 360, 1406], "text": "Manages", "label": "other", "id": 191, "words": [{"box": [239, 1375, 360, 1406], "text": "Manages"}]}, {"box": [367, 1375, 419, 1406], "text": "and", "label": "other", "id": 192, "words": [{"box": [367, 1375, 419, 1406], "text": "and"}]}, {"box": [426, 1375, 556, 1406], "text": "maintains", "label": "other", "id": 193, "words": [{"box": [426, 1375, 556, 1406], "text": "maintains"}]}, {"box": [564, 1375, 604, 1406], "text": "HR", "label": "other", "id": 194, "words": [{"box": [564, 1375, 604, 1406], "text": "HR"}]}, {"box": [611, 1375, 669, 1406], "text": "VP\u2019s", "label": "other", "id": 195, "words": [{"box": [611, 1375, 669, 1406], "text": "VP\u2019s"}]}, {"box": [676, 1375, 811, 1406], "text": "calendars,", "label": "other", "id": 196, "words": [{"box": [676, 1375, 811, 1406], "text": "calendars,"}]}, {"box": [819, 1375, 937, 1406], "text": "schedule", "label": "other", "id": 197, "words": [{"box": [819, 1375, 937, 1406], "text": "schedule"}]}, {"box": [944, 1375, 1137, 1406], "text": "appointments,", "label": "other", "id": 198, "words": [{"box": [944, 1375, 1137, 1406], "text": "appointments,"}]}, {"box": [1145, 1375, 1301, 1406], "text": "coordinates", "label": "other", "id": 199, "words": [{"box": [1145, 1375, 1301, 1406], "text": "coordinates"}]}, {"box": [1309, 1375, 1439, 1406], "text": "meetings,", "label": "other", "id": 200, "words": [{"box": [1309, 1375, 1439, 1406], "text": "meetings,"}]}, {"box": [239, 1413, 313, 1444], "text": "video", "label": "other", "id": 201, "words": [{"box": [239, 1413, 313, 1444], "text": "video"}]}, {"box": [318, 1413, 342, 1444], "text": "&", "label": "other", "id": 202, "words": [{"box": [318, 1413, 342, 1444], "text": "&"}]}, {"box": [347, 1413, 496, 1444], "text": "conference", "label": "other", "id": 203, "words": [{"box": [347, 1413, 496, 1444], "text": "conference"}]}, {"box": [500, 1413, 559, 1444], "text": "calls", "label": "other", "id": 204, "words": [{"box": [500, 1413, 559, 1444], "text": "calls"}]}, {"box": [564, 1413, 649, 1444], "text": "across", "label": "other", "id": 205, "words": [{"box": [564, 1413, 649, 1444], "text": "across"}]}, {"box": [654, 1413, 784, 1444], "text": "Americas,", "label": "other", "id": 206, "words": [{"box": [654, 1413, 784, 1444], "text": "Americas,"}]}, {"box": [789, 1413, 845, 1444], "text": "Asia", "label": "other", "id": 207, "words": [{"box": [789, 1413, 845, 1444], "text": "Asia"}]}, {"box": [850, 1413, 936, 1444], "text": "Pacific", "label": "other", "id": 208, "words": [{"box": [850, 1413, 936, 1444], "text": "Pacific"}]}, {"box": [941, 1413, 992, 1444], "text": "and", "label": "other", "id": 209, "words": [{"box": [941, 1413, 992, 1444], "text": "and"}]}, {"box": [993, 1413, 1146, 1444], "text": "Australasia.", "label": "other", "id": 210, "words": [{"box": [993, 1413, 1146, 1444], "text": "Australasia."}]}, {"box": [239, 1492, 355, 1522], "text": "Assisting", "label": "other", "id": 211, "words": [{"box": [239, 1492, 355, 1522], "text": "Assisting"}]}, {"box": [366, 1492, 406, 1522], "text": "HR", "label": "other", "id": 212, "words": [{"box": [366, 1492, 406, 1522], "text": "HR"}]}, {"box": [417, 1492, 454, 1522], "text": "VP", "label": "other", "id": 213, "words": [{"box": [417, 1492, 454, 1522], "text": "VP"}]}, {"box": [466, 1492, 526, 1522], "text": "with", "label": "other", "id": 214, "words": [{"box": [466, 1492, 526, 1522], "text": "with"}]}, {"box": [537, 1492, 570, 1522], "text": "all", "label": "other", "id": 215, "words": [{"box": [537, 1492, 570, 1522], "text": "all"}]}, {"box": [582, 1492, 751, 1522], "text": "employment", "label": "other", "id": 216, "words": [{"box": [582, 1492, 751, 1522], "text": "employment"}]}, {"box": [762, 1492, 843, 1522], "text": "issues", "label": "other", "id": 217, "words": [{"box": [762, 1492, 843, 1522], "text": "issues"}]}, {"box": [854, 1492, 895, 1522], "text": "for", "label": "other", "id": 218, "words": [{"box": [854, 1492, 895, 1522], "text": "for"}]}, {"box": [905, 1492, 941, 1522], "text": "50", "label": "other", "id": 219, "words": [{"box": [905, 1492, 941, 1522], "text": "50"}]}, {"box": [952, 1492, 1015, 1522], "text": "local", "label": "other", "id": 220, "words": [{"box": [952, 1492, 1015, 1522], "text": "local"}]}, {"box": [1026, 1492, 1171, 1522], "text": "employees", "label": "other", "id": 221, "words": [{"box": [1026, 1492, 1171, 1522], "text": "employees"}]}, {"box": [1182, 1492, 1234, 1522], "text": "and", "label": "other", "id": 222, "words": [{"box": [1182, 1492, 1234, 1522], "text": "and"}]}, {"box": [1245, 1492, 1280, 1522], "text": "55", "label": "other", "id": 223, "words": [{"box": [1245, 1492, 1280, 1522], "text": "55"}]}, {"box": [1291, 1492, 1440, 1522], "text": "expatriates", "label": "other", "id": 224, "words": [{"box": [1291, 1492, 1440, 1522], "text": "expatriates"}]}, {"box": [239, 1530, 359, 1561], "text": "including", "label": "other", "id": 225, "words": [{"box": [239, 1530, 359, 1561], "text": "including"}]}, {"box": [365, 1530, 514, 1561], "text": "completing", "label": "other", "id": 226, "words": [{"box": [365, 1530, 514, 1561], "text": "completing"}]}, {"box": [520, 1530, 579, 1561], "text": "new", "label": "other", "id": 227, "words": [{"box": [520, 1530, 579, 1561], "text": "new"}]}, {"box": [585, 1530, 733, 1561], "text": "enrolment,", "label": "other", "id": 228, "words": [{"box": [585, 1530, 733, 1561], "text": "enrolment,"}]}, {"box": [739, 1530, 848, 1561], "text": "changes", "label": "other", "id": 229, "words": [{"box": [739, 1530, 848, 1561], "text": "changes"}]}, {"box": [854, 1530, 906, 1561], "text": "and", "label": "other", "id": 230, "words": [{"box": [854, 1530, 906, 1561], "text": "and"}]}, {"box": [912, 1530, 1082, 1561], "text": "terminations", "label": "other", "id": 231, "words": [{"box": [912, 1530, 1082, 1561], "text": "terminations"}]}, {"box": [1088, 1530, 1169, 1561], "text": "under", "label": "other", "id": 232, "words": [{"box": [1088, 1530, 1169, 1561], "text": "under"}]}, {"box": [1175, 1530, 1221, 1561], "text": "the", "label": "other", "id": 233, "words": [{"box": [1175, 1530, 1221, 1561], "text": "the"}]}, {"box": [1227, 1530, 1279, 1561], "text": "SAP", "label": "other", "id": 234, "words": [{"box": [1227, 1530, 1279, 1561], "text": "SAP"}]}, {"box": [1286, 1530, 1383, 1561], "text": "System", "label": "other", "id": 235, "words": [{"box": [1286, 1530, 1383, 1561], "text": "System"}]}, {"box": [1389, 1530, 1440, 1561], "text": "and", "label": "other", "id": 236, "words": [{"box": [1389, 1530, 1440, 1561], "text": "and"}]}, {"box": [239, 1569, 318, 1600], "text": "MOM", "label": "other", "id": 237, "words": [{"box": [239, 1569, 318, 1600], "text": "MOM"}]}, {"box": [322, 1569, 406, 1600], "text": "online", "label": "other", "id": 238, "words": [{"box": [322, 1569, 406, 1600], "text": "online"}]}, {"box": [410, 1569, 572, 1600], "text": "registration.", "label": "other", "id": 239, "words": [{"box": [410, 1569, 572, 1600], "text": "registration."}]}, {"box": [239, 1657, 398, 1687], "text": "Responsible", "label": "other", "id": 240, "words": [{"box": [239, 1657, 398, 1687], "text": "Responsible"}]}, {"box": [403, 1657, 443, 1687], "text": "for", "label": "other", "id": 241, "words": [{"box": [403, 1657, 443, 1687], "text": "for"}]}, {"box": [448, 1657, 538, 1687], "text": "review", "label": "other", "id": 242, "words": [{"box": [448, 1657, 538, 1687], "text": "review"}]}, {"box": [543, 1657, 573, 1687], "text": "of", "label": "other", "id": 243, "words": [{"box": [543, 1657, 573, 1687], "text": "of"}]}, {"box": [577, 1657, 689, 1687], "text": "monthly", "label": "other", "id": 244, "words": [{"box": [577, 1657, 689, 1687], "text": "monthly"}]}, {"box": [694, 1657, 801, 1687], "text": "invoices", "label": "other", "id": 245, "words": [{"box": [694, 1657, 801, 1687], "text": "invoices"}]}, {"box": [806, 1657, 872, 1687], "text": "from", "label": "other", "id": 246, "words": [{"box": [806, 1657, 872, 1687], "text": "from"}]}, {"box": [877, 1657, 910, 1687], "text": "all", "label": "other", "id": 247, "words": [{"box": [877, 1657, 910, 1687], "text": "all"}]}, {"box": [914, 1657, 1010, 1687], "text": "benefit", "label": "other", "id": 248, "words": [{"box": [914, 1657, 1010, 1687], "text": "benefit"}]}, {"box": [1015, 1657, 1124, 1687], "text": "carriers,", "label": "other", "id": 249, "words": [{"box": [1015, 1657, 1124, 1687], "text": "carriers,"}]}, {"box": [1129, 1657, 1231, 1687], "text": "process", "label": "other", "id": 250, "words": [{"box": [1129, 1657, 1231, 1687], "text": "process"}]}, {"box": [1236, 1657, 1269, 1687], "text": "all", "label": "other", "id": 251, "words": [{"box": [1236, 1657, 1269, 1687], "text": "all"}]}, {"box": [1273, 1657, 1381, 1687], "text": "invoices", "label": "other", "id": 252, "words": [{"box": [1273, 1657, 1381, 1687], "text": "invoices"}]}, {"box": [1388, 1657, 1440, 1687], "text": "and", "label": "other", "id": 253, "words": [{"box": [1388, 1657, 1440, 1687], "text": "and"}]}, {"box": [239, 1695, 330, 1726], "text": "ensure", "label": "other", "id": 254, "words": [{"box": [239, 1695, 330, 1726], "text": "ensure"}]}, {"box": [335, 1695, 419, 1726], "text": "timely", "label": "other", "id": 255, "words": [{"box": [335, 1695, 419, 1726], "text": "timely"}]}, {"box": [424, 1695, 572, 1726], "text": "submission", "label": "other", "id": 256, "words": [{"box": [424, 1695, 572, 1726], "text": "submission"}]}, {"box": [576, 1695, 607, 1726], "text": "to", "label": "other", "id": 257, "words": [{"box": [576, 1695, 607, 1726], "text": "to"}]}, {"box": [611, 1695, 733, 1726], "text": "Accounts", "label": "other", "id": 258, "words": [{"box": [611, 1695, 733, 1726], "text": "Accounts"}]}, {"box": [738, 1695, 897, 1726], "text": "department", "label": "other", "id": 259, "words": [{"box": [738, 1695, 897, 1726], "text": "department"}]}, {"box": [901, 1695, 942, 1726], "text": "for", "label": "other", "id": 260, "words": [{"box": [901, 1695, 942, 1726], "text": "for"}]}, {"box": [944, 1695, 1071, 1726], "text": "payment.", "label": "other", "id": 261, "words": [{"box": [944, 1695, 1071, 1726], "text": "payment."}]}, {"box": [239, 1774, 399, 1805], "text": "Coordinates", "label": "other", "id": 262, "words": [{"box": [239, 1774, 399, 1805], "text": "Coordinates"}]}, {"box": [410, 1774, 461, 1805], "text": "and", "label": "other", "id": 263, "words": [{"box": [410, 1774, 461, 1805], "text": "and"}]}, {"box": [472, 1774, 558, 1805], "text": "liaison", "label": "other", "id": 264, "words": [{"box": [472, 1774, 558, 1805], "text": "liaison"}]}, {"box": [569, 1774, 598, 1805], "text": "of", "label": "other", "id": 265, "words": [{"box": [569, 1774, 598, 1805], "text": "of"}]}, {"box": [609, 1774, 672, 1805], "text": "local", "label": "other", "id": 266, "words": [{"box": [609, 1774, 672, 1805], "text": "local"}]}, {"box": [683, 1774, 843, 1805], "text": "permanent/", "label": "other", "id": 267, "words": [{"box": [683, 1774, 843, 1805], "text": "permanent/"}]}, {"box": [853, 1774, 994, 1805], "text": "temporary", "label": "other", "id": 268, "words": [{"box": [853, 1774, 994, 1805], "text": "temporary"}]}, {"box": [1004, 1774, 1110, 1805], "text": "housing", "label": "other", "id": 269, "words": [{"box": [1004, 1774, 1110, 1805], "text": "housing"}]}, {"box": [1120, 1774, 1181, 1805], "text": "with", "label": "other", "id": 270, "words": [{"box": [1120, 1774, 1181, 1805], "text": "with"}]}, {"box": [1191, 1774, 1322, 1805], "text": "corporate", "label": "other", "id": 271, "words": [{"box": [1191, 1774, 1322, 1805], "text": "corporate"}]}, {"box": [1333, 1774, 1438, 1805], "text": "housing", "label": "other", "id": 272, "words": [{"box": [1333, 1774, 1438, 1805], "text": "housing"}]}, {"box": [239, 1813, 328, 1844], "text": "agents", "label": "other", "id": 273, "words": [{"box": [239, 1813, 328, 1844], "text": "agents"}]}, {"box": [340, 1813, 392, 1844], "text": "and", "label": "other", "id": 274, "words": [{"box": [340, 1813, 392, 1844], "text": "and"}]}, {"box": [404, 1813, 496, 1844], "text": "ensure", "label": "other", "id": 275, "words": [{"box": [404, 1813, 496, 1844], "text": "ensure"}]}, {"box": [508, 1813, 610, 1844], "text": "smooth", "label": "other", "id": 276, "words": [{"box": [508, 1813, 610, 1844], "text": "smooth"}]}, {"box": [623, 1813, 750, 1844], "text": "handover", "label": "other", "id": 277, "words": [{"box": [623, 1813, 750, 1844], "text": "handover"}]}, {"box": [762, 1813, 791, 1844], "text": "of", "label": "other", "id": 278, "words": [{"box": [762, 1813, 791, 1844], "text": "of"}]}, {"box": [803, 1813, 925, 1844], "text": "tenanted", "label": "other", "id": 279, "words": [{"box": [803, 1813, 925, 1844], "text": "tenanted"}]}, {"box": [937, 1813, 1195, 1844], "text": "apartments/houses", "label": "other", "id": 280, "words": [{"box": [937, 1813, 1195, 1844], "text": "apartments/houses"}]}, {"box": [1207, 1813, 1296, 1844], "text": "before", "label": "other", "id": 281, "words": [{"box": [1207, 1813, 1296, 1844], "text": "before"}]}, {"box": [1309, 1813, 1360, 1844], "text": "and", "label": "other", "id": 282, "words": [{"box": [1309, 1813, 1360, 1844], "text": "and"}]}, {"box": [1372, 1813, 1439, 1844], "text": "after", "label": "other", "id": 283, "words": [{"box": [1372, 1813, 1439, 1844], "text": "after"}]}, {"box": [239, 1852, 395, 1882], "text": "expatriates\u2019", "label": "other", "id": 284, "words": [{"box": [239, 1852, 395, 1882], "text": "expatriates\u2019"}]}, {"box": [400, 1852, 466, 1882], "text": "term", "label": "other", "id": 285, "words": [{"box": [400, 1852, 466, 1882], "text": "term"}]}, {"box": [470, 1852, 498, 1882], "text": "in", "label": "other", "id": 286, "words": [{"box": [470, 1852, 498, 1882], "text": "in"}]}, {"box": [502, 1852, 643, 1882], "text": "Singapore.", "label": "other", "id": 287, "words": [{"box": [502, 1852, 643, 1882], "text": "Singapore."}]}, {"box": [239, 1931, 396, 1961], "text": "Preparation", "label": "other", "id": 288, "words": [{"box": [239, 1931, 396, 1961], "text": "Preparation"}]}, {"box": [399, 1931, 451, 1961], "text": "and", "label": "other", "id": 289, "words": [{"box": [399, 1931, 451, 1961], "text": "and"}]}, {"box": [454, 1931, 548, 1961], "text": "vetting", "label": "other", "id": 290, "words": [{"box": [454, 1931, 548, 1961], "text": "vetting"}]}, {"box": [552, 1931, 581, 1961], "text": "of", "label": "other", "id": 291, "words": [{"box": [552, 1931, 581, 1961], "text": "of"}]}, {"box": [585, 1931, 691, 1961], "text": "tenancy", "label": "other", "id": 292, "words": [{"box": [585, 1931, 691, 1961], "text": "tenancy"}]}, {"box": [695, 1931, 853, 1961], "text": "agreements", "label": "other", "id": 293, "words": [{"box": [695, 1931, 853, 1961], "text": "agreements"}]}, {"box": [856, 1931, 897, 1961], "text": "for", "label": "other", "id": 294, "words": [{"box": [856, 1931, 897, 1961], "text": "for"}]}, {"box": [901, 1931, 1032, 1961], "text": "corporate", "label": "other", "id": 295, "words": [{"box": [901, 1931, 1032, 1961], "text": "corporate"}]}, {"box": [1036, 1931, 1141, 1961], "text": "housing", "label": "other", "id": 296, "words": [{"box": [1036, 1931, 1141, 1961], "text": "housing"}]}, {"box": [1144, 1931, 1227, 1961], "text": "leases", "label": "other", "id": 297, "words": [{"box": [1144, 1931, 1227, 1961], "text": "leases"}]}, {"box": [1231, 1931, 1271, 1961], "text": "for", "label": "other", "id": 298, "words": [{"box": [1231, 1931, 1271, 1961], "text": "for"}]}, {"box": [1274, 1931, 1431, 1961], "text": "expatriates.", "label": "other", "id": 299, "words": [{"box": [1274, 1931, 1431, 1961], "text": "expatriates."}]}, {"box": [239, 2018, 399, 2049], "text": "Coordinates", "label": "other", "id": 300, "words": [{"box": [239, 2018, 399, 2049], "text": "Coordinates"}]}, {"box": [409, 2018, 461, 2049], "text": "and", "label": "other", "id": 301, "words": [{"box": [409, 2018, 461, 2049], "text": "and"}]}, {"box": [471, 2018, 558, 2049], "text": "liaison", "label": "other", "id": 302, "words": [{"box": [471, 2018, 558, 2049], "text": "liaison"}]}, {"box": [568, 2018, 629, 2049], "text": "with", "label": "other", "id": 303, "words": [{"box": [568, 2018, 629, 2049], "text": "with"}]}, {"box": [639, 2018, 751, 2049], "text": "shipping", "label": "other", "id": 304, "words": [{"box": [639, 2018, 751, 2049], "text": "shipping"}]}, {"box": [761, 2018, 884, 2049], "text": "company", "label": "other", "id": 305, "words": [{"box": [761, 2018, 884, 2049], "text": "company"}]}, {"box": [895, 2018, 931, 2049], "text": "on", "label": "other", "id": 306, "words": [{"box": [895, 2018, 931, 2049], "text": "on"}]}, {"box": [941, 2018, 1026, 2049], "text": "timely", "label": "other", "id": 307, "words": [{"box": [941, 2018, 1026, 2049], "text": "timely"}]}, {"box": [1036, 2018, 1264, 2049], "text": "arrival/departure", "label": "other", "id": 308, "words": [{"box": [1036, 2018, 1264, 2049], "text": "arrival/departure"}]}, {"box": [1274, 2018, 1304, 2049], "text": "of", "label": "other", "id": 309, "words": [{"box": [1274, 2018, 1304, 2049], "text": "of"}]}, {"box": [1314, 2018, 1439, 2049], "text": "shipment", "label": "other", "id": 310, "words": [{"box": [1314, 2018, 1439, 2049], "text": "shipment"}]}, {"box": [239, 2057, 279, 2087], "text": "for", "label": "other", "id": 311, "words": [{"box": [239, 2057, 279, 2087], "text": "for"}]}, {"box": [283, 2057, 405, 2087], "text": "incoming", "label": "other", "id": 312, "words": [{"box": [283, 2057, 405, 2087], "text": "incoming"}]}, {"box": [410, 2057, 462, 2087], "text": "and", "label": "other", "id": 313, "words": [{"box": [410, 2057, 462, 2087], "text": "and"}]}, {"box": [466, 2057, 585, 2087], "text": "outgoing", "label": "other", "id": 314, "words": [{"box": [466, 2057, 585, 2087], "text": "outgoing"}]}, {"box": [589, 2057, 745, 2087], "text": "expatriates.", "label": "other", "id": 315, "words": [{"box": [589, 2057, 745, 2087], "text": "expatriates."}]}]}